MANIFEST.in
README.txt
setup.py
docs/HISTORY.txt
docs/LICENSE.txt
src/__init__.py
src/localdatetime/__init__.py
src/localdatetime/tests.py
src/z3locales.egg-info/PKG-INFO
src/z3locales.egg-info/SOURCES.txt
src/z3locales.egg-info/dependency_links.txt
src/z3locales.egg-info/requires.txt
src/z3locales.egg-info/top_level.txt
src/z3locales.egg-info/zip-safe