Metadata-Version: 1.0
Name: z3locales
Version: 0.4.1
Summary: Display localized dates in Zope 2 using Zope 3 components.
Home-page: http://infrae.com/download/z3locales
Author: Guido Wesdorp
Author-email: info@infrae.com
License: ZPL 2.1
Keywords: internationalization zope2 zope3 i18n
Platform: UNKNOWN
Classifier: Framework :: Zope2
Classifier: Framework :: Zope3
Classifier: License :: OSI Approved :: Zope Public License
Classifier: Topic :: Software Development :: Internationalization
Classifier: Programming Language :: Python
Classifier: Topic :: Software Development :: Libraries :: Python Modules
